cookiemonster/__init__.py
cookiemonster/app.py
cookiemonster-0.0.1.dist-info/LICENSE
cookiemonster-0.0.1.dist-info/METADATA
cookiemonster-0.0.1.dist-info/WHEEL
cookiemonster-0.0.1.dist-info/entry_points.txt
cookiemonster-0.0.1.dist-info/top_level.txt
cookiemonster-0.0.1.dist-info/RECORD
